{
  "posts": {
    "_posts": [
      "../index.md"
    ],
    "algorithms": {
      "greedy_algorithms": {
        "_posts": [
          "minimum_spanning_tree"
        ]
      }
    },
    "go": {
      "basics": {
        "_posts": [
          "module",
          "variable_and_constant",
          "struct",
          "if_statement",
          "switch_statement",
          "loop",
          "array"
        ]
      }
    },
    "cpp": {
      "basics": {
        "_posts": [
          "constructor"
        ]
      }
    },
    "web": {
      "html": {
        "_posts": [
          "basics"
        ]
      }
    }
  }
}